common/__init__.py
common/dict_util.py
common/exceptions.py
common/log.py
common/models.py
common/binance/__init__.py
common/binance/check.py
common/binance/constant.py
common/binance/service.py
common/binance/utils.py
common/binance/wallet.py
common/huobi/__init__.py
common/huobi/account_service.py
common/huobi/client.py
common/huobi/constants.py
common/huobi/exceptions.py
common/huobi/future.py
common/huobi/service.py
common/huobi/stream.py
common/huobi/tools.py
common/huobi/utils.py
common/huobi/wallet.py
common/okex/__init__.py
common/okex/client.py
common/okex/constants.py
common/okex/error_code.py
common/okex/exceptions.py
common/okex/service.py
common/okex/stream.py
common/okex/tools.py
common/okex/utils.py
common/utils/__init__.py
common/utils/dict_util.py
common/utils/binance/__init__.py
common/utils/binance/check.py
common/utils/huobi/__init__.py
gecko_common-0.1.94.dist-info/LICENSE
gecko_common-0.1.94.dist-info/METADATA
gecko_common-0.1.94.dist-info/WHEEL
gecko_common-0.1.94.dist-info/top_level.txt
gecko_common-0.1.94.dist-info/RECORD
