Metadata-Version: 2.1
Name: gecko-common
Version: 0.1.94
Summary: gecko common library
Home-page: https://gitlab.com/winwin2021/common
Author: sgy
Author-email: ericsgy@163.com
License: MIT
Keywords: binance huobi ok exchange
Platform: UNKNOWN
Classifier: Development Status :: 3 - Alpha
Classifier: Intended Audience :: Developers
Classifier: Topic :: Software Development :: Libraries :: Python Modules
Classifier: License :: OSI Approved :: MIT License
Classifier: Programming Language :: Python :: 3.7
Requires-Python: >=3.7
License-File: LICENSE
Requires-Dist: aiohttp (<=4,>=3.6.2)
Requires-Dist: python-binance2
